{"type":"FeatureCollection","features":[{"type":"Feature","id":23673,"properties":{"rag":"r","type":"OHL 230V 50 OAL","v":230},"geometry":{"type":"LineString","coordinates":[[-4.43233,53.37173],[-4.4319,53.37179],[-4.43168,53.37127],[-4.43162,53.37085],[-4.43177,53.37036],[-4.43152,53.3702]]}},{"type":"Feature","id":23676,"properties":{"rag":"r","type":"OHL 230V 50 OAL","v":230},"geometry":{"type":"LineString","coordinates":[[-4.42567,53.36851],[-4.42589,53.3682],[-4.4261,53.36791],[-4.42635,53.36759]]}},{"type":"Feature","id":23681,"properties":{"rag":"r","type":"OHL 230V 50 OAL","v":230},"geometry":{"type":"LineString","coordinates":[[-4.41993,53.35802],[-4.41933,53.35833],[-4.41869,53.35866],[-4.41821,53.35905],[-4.41788,53.3594],[-4.41732,53.35971]]}},{"type":"Feature","id":23710,"properties":{"rag":"r","type":"OHL 230V 50 OAL","v":230},"geometry":{"type":"LineString","coordinates":[[-4.41923,53.35904],[-4.41913,53.35897]]}},{"type":"Feature","id":23719,"properties":{"rag":"r","type":"OHL 230V 50 OAL","v":230},"geometry":{"type":"LineString","coordinates":[[-4.43027,53.36603],[-4.43079,53.36609]]}},{"type":"Feature","id":23722,"properties":{"rag":"r","type":"OHL 230V 50 OAL","v":230},"geometry":{"type":"LineString","coordinates":[[-4.42549,53.36875],[-4.42565,53.36853]]}},{"type":"Feature","id":47022,"properties":{"rag":"r","type":"UNKNOWN_LV_OHLine_M","v":230},"geometry":{"type":"LineString","coordinates":[[-4.41913,53.35897],[-4.41876,53.35871],[-4.41869,53.35866]]}},{"type":"Feature","id":92937,"properties":{"rag":"r","type":"OHL 230V 25 OAL","v":230},"geometry":{"type":"LineString","coordinates":[[-4.4319,53.37012],[-4.43177,53.37036]]}}]}