{"type":"FeatureCollection","features":[{"type":"Feature","id":17786,"properties":{"rag":"r","type":"OHL 230V 50 OAL","v":230},"geometry":{"type":"LineString","coordinates":[[-2.83841,52.96267],[-2.83801,52.96296],[-2.83744,52.96319],[-2.83691,52.9634]]}},{"type":"Feature","id":17789,"properties":{"rag":"r","type":"OHL 230V 50 OAL","v":230},"geometry":{"type":"LineString","coordinates":[[-2.84615,52.97092],[-2.84589,52.97063]]}},{"type":"Feature","id":17800,"properties":{"rag":"r","type":"OHL 230V 50 OAL","v":230},"geometry":{"type":"LineString","coordinates":[[-2.84207,52.96447],[-2.84206,52.96448],[-2.84206,52.96477]]}},{"type":"Feature","id":17805,"properties":{"rag":"r","type":"OHL 230V 50 OAL","v":230},"geometry":{"type":"LineString","coordinates":[[-2.84876,52.9741],[-2.84948,52.97417]]}},{"type":"Feature","id":17809,"properties":{"rag":"r","type":"OHL 230V 50 OAL","v":230},"geometry":{"type":"LineString","coordinates":[[-2.84654,52.97241],[-2.84658,52.97204],[-2.84663,52.97154]]}},{"type":"Feature","id":17816,"properties":{"rag":"r","type":"OHL 230V 50 OAL","v":230},"geometry":{"type":"LineString","coordinates":[[-2.85317,52.97082],[-2.85347,52.97111],[-2.85411,52.97139],[-2.85458,52.97158],[-2.85537,52.97191],[-2.85605,52.97219]]}},{"type":"Feature","id":24316,"properties":{"rag":"r","type":"OHL 230V 0.05 OAL","v":230},"geometry":{"type":"LineString","coordinates":[[-2.84267,52.9638],[-2.8423,52.96413],[-2.84207,52.96447]]}},{"type":"Feature","id":24329,"properties":{"rag":"r","type":"OHL 230V 0.05 OAL","v":230},"geometry":{"type":"LineString","coordinates":[[-2.84876,52.9741],[-2.84815,52.97403]]}},{"type":"Feature","id":24333,"properties":{"rag":"r","type":"OHL 230V 0.05 OAL","v":230},"geometry":{"type":"LineString","coordinates":[[-2.851,52.96942],[-2.85025,52.96961],[-2.84972,52.96974]]}},{"type":"Feature","id":24338,"properties":{"rag":"r","type":"OHL 230V 0.05 OAL","v":230},"geometry":{"type":"LineString","coordinates":[[-2.85355,52.96136],[-2.85349,52.96183],[-2.85345,52.96213],[-2.85328,52.96253],[-2.85278,52.96301],[-2.85231,52.96348]]}},{"type":"Feature","id":41461,"properties":{"rag":"r","type":"UNKNOWN_LV_OHLine_M","v":230},"geometry":{"type":"LineString","coordinates":[[-2.8387,52.96249],[-2.83867,52.96251],[-2.83841,52.96267],[-2.8387,52.96296],[-2.83902,52.96327],[-2.83943,52.96339],[-2.84004,52.96339]]}},{"type":"Feature","id":41472,"properties":{"rag":"r","type":"UNKNOWN_LV_OHLine_M","v":230},"geometry":{"type":"LineString","coordinates":[[-2.84921,52.96909],[-2.84972,52.96974],[-2.8497,52.97007]]}},{"type":"Feature","id":41481,"properties":{"rag":"r","type":"UNKNOWN_LV_OHLine_M","v":230},"geometry":{"type":"LineString","coordinates":[[-2.84644,52.97125],[-2.84615,52.97092]]}},{"type":"Feature","id":41486,"properties":{"rag":"r","type":"UNKNOWN_LV_OHLine_M","v":230},"geometry":{"type":"LineString","coordinates":[[-2.83872,52.96247],[-2.83882,52.96244],[-2.83919,52.96229]]}},{"type":"Feature","id":41503,"properties":{"rag":"r","type":"UNKNOWN_LV_OHLine_M","v":230},"geometry":{"type":"LineString","coordinates":[[-2.85458,52.97158],[-2.85486,52.97127],[-2.85487,52.97127]]}},{"type":"Feature","id":41510,"properties":{"rag":"r","type":"UNKNOWN_LV_OHLine_M","v":230},"geometry":{"type":"LineString","coordinates":[[-2.85179,52.96359],[-2.85229,52.96349]]}},{"type":"Feature","id":47614,"properties":{"rag":"r","type":"Cable 230V 95 AL","v":230},"geometry":{"type":"LineString","coordinates":[[-2.84206,52.96477],[-2.84211,52.96478],[-2.84212,52.96477],[-2.84214,52.96476],[-2.84219,52.96473],[-2.8422,52.96472],[-2.8422,52.96472],[-2.84221,52.96472],[-2.84221,52.96472],[-2.84253,52.96489],[-2.8426,52.96494],[-2.8426,52.96495],[-2.8426,52.96496],[-2.84255,52.96501],[-2.84251,52.96506],[-2.8425,52.96508],[-2.84248,52.9651],[-2.84245,52.96518]]}},{"type":"Feature","id":47622,"properties":{"rag":"r","type":"Cable 230V 95 AL","v":230},"geometry":{"type":"LineString","coordinates":[[-2.84815,52.97403],[-2.84798,52.97404],[-2.84797,52.97404],[-2.84796,52.97404],[-2.84795,52.97404],[-2.84794,52.97404],[-2.84791,52.97402],[-2.84785,52.974],[-2.84774,52.97393]]}},{"type":"Feature","id":47632,"properties":{"rag":"r","type":"Cable 230V 95 AL","v":230},"geometry":{"type":"LineString","coordinates":[[-2.85095,52.96351],[-2.85106,52.96367],[-2.85107,52.96367],[-2.85108,52.96368],[-2.85109,52.96368],[-2.8511,52.96368],[-2.85111,52.96368],[-2.85129,52.96365],[-2.85142,52.96362],[-2.85159,52.96357],[-2.85159,52.96357],[-2.8516,52.96357],[-2.85179,52.96359]]}},{"type":"Feature","id":47639,"properties":{"rag":"r","type":"Cable 230V 95 AL","v":230},"geometry":{"type":"LineString","coordinates":[[-2.85139,52.97499],[-2.85134,52.97499],[-2.85122,52.97512],[-2.85168,52.97525]]}},{"type":"Feature","id":47641,"properties":{"rag":"r","type":"Cable 230V 95 AL","v":230},"geometry":{"type":"LineString","coordinates":[[-2.85487,52.97127],[-2.85487,52.97126],[-2.85487,52.97125],[-2.85505,52.97103]]}},{"type":"Feature","id":82418,"properties":{"rag":"r","type":"OHL 230V 0.025 OCU","v":230},"geometry":{"type":"LineString","coordinates":[[-2.84644,52.97126],[-2.84663,52.97154]]}},{"type":"Feature","id":179079,"properties":{"rag":"r","type":"UNKNOWN_LV_Cable_M","v":230},"geometry":{"type":"LineString","coordinates":[[-2.84815,52.97403],[-2.84811,52.97398],[-2.8481,52.97398],[-2.84809,52.97398],[-2.84803,52.97394],[-2.84802,52.97394],[-2.84801,52.97393],[-2.84799,52.97393],[-2.84798,52.97392],[-2.84796,52.97392],[-2.84795,52.97391],[-2.84777,52.97378]]}},{"type":"Feature","id":179083,"properties":{"rag":"r","type":"UNKNOWN_LV_Cable_M","v":230},"geometry":{"type":"LineString","coordinates":[[-2.85315,52.97081],[-2.85312,52.97078],[-2.85308,52.97075],[-2.85305,52.97073],[-2.85303,52.97072],[-2.85297,52.97067],[-2.85294,52.97065],[-2.85289,52.97061],[-2.85287,52.9706],[-2.85286,52.97059],[-2.85286,52.97058],[-2.85287,52.97057],[-2.85288,52.97057],[-2.8529,52.97056],[-2.85292,52.97055],[-2.85293,52.97054]]}},{"type":"Feature","id":179092,"properties":{"rag":"r","type":"UNKNOWN_LV_Cable_M","v":230},"geometry":{"type":"LineString","coordinates":[[-2.85095,52.96351],[-2.85089,52.96343]]}},{"type":"Feature","id":204636,"properties":{"rag":"x","type":"Cable 230V 95 AL","v":230},"geometry":{"type":"LineString","coordinates":[[-2.84644,52.97125],[-2.84675,52.97114],[-2.84676,52.97113],[-2.84677,52.97112],[-2.84683,52.97102],[-2.84689,52.97097]]}}]}