{"type":"FeatureCollection","features":[{"type":"Feature","id":20553,"properties":{"rag":"r","type":"OHL 230V 50 OAL","v":230},"geometry":{"type":"LineString","coordinates":[[-3.70442,53.18424],[-3.70446,53.18451]]}},{"type":"Feature","id":20563,"properties":{"rag":"r","type":"OHL 230V 50 OAL","v":230},"geometry":{"type":"LineString","coordinates":[[-3.69956,53.1767],[-3.70019,53.17652],[-3.70105,53.17634]]}},{"type":"Feature","id":20566,"properties":{"rag":"r","type":"OHL 230V 50 OAL","v":230},"geometry":{"type":"LineString","coordinates":[[-3.69954,53.17671],[-3.69905,53.17705],[-3.6986,53.17735]]}},{"type":"Feature","id":25944,"properties":{"rag":"r","type":"OHL 230V 0.05 OAL","v":230},"geometry":{"type":"LineString","coordinates":[[-3.69724,53.17723],[-3.69716,53.17769]]}},{"type":"Feature","id":44052,"properties":{"rag":"r","type":"UNKNOWN_LV_OHLine_M","v":230},"geometry":{"type":"LineString","coordinates":[[-3.70131,53.17638],[-3.70105,53.17634]]}},{"type":"Feature","id":91787,"properties":{"rag":"r","type":"OHL 230V 95 ABC","v":230},"geometry":{"type":"LineString","coordinates":[[-3.7052,53.18548],[-3.70502,53.18523],[-3.70479,53.18495],[-3.70446,53.18451]]}},{"type":"Feature","id":91794,"properties":{"rag":"r","type":"OHL 230V 95 ABC","v":230},"geometry":{"type":"LineString","coordinates":[[-3.69101,53.17865],[-3.69141,53.17835]]}}]}