{"type":"FeatureCollection","features":[{"type":"Feature","id":21885,"properties":{"rag":"r","type":"OHL 230V 50 OAL","v":230},"geometry":{"type":"LineString","coordinates":[[-3.18367,53.24586],[-3.18454,53.24608]]}},{"type":"Feature","id":21901,"properties":{"rag":"r","type":"OHL 230V 50 OAL","v":230},"geometry":{"type":"LineString","coordinates":[[-3.18443,53.24955],[-3.18412,53.2495],[-3.18351,53.24931],[-3.18278,53.24902]]}},{"type":"Feature","id":26761,"properties":{"rag":"r","type":"OHL 230V 0.05 OAL","v":230},"geometry":{"type":"LineString","coordinates":[[-3.17391,53.24528],[-3.17375,53.24482],[-3.17365,53.24447]]}},{"type":"Feature","id":40389,"properties":{"rag":"a","type":"UNKNOWN_LV_OHLine_M","v":230},"geometry":{"type":"LineString","coordinates":[[-3.17753,53.24549],[-3.17756,53.24545]]}},{"type":"Feature","id":40403,"properties":{"rag":"a","type":"UNKNOWN_LV_OHLine_M","v":230},"geometry":{"type":"LineString","coordinates":[[-3.17923,53.24691],[-3.17946,53.24669]]}},{"type":"Feature","id":46211,"properties":{"rag":"r","type":"UNKNOWN_LV_OHLine_M","v":230},"geometry":{"type":"LineString","coordinates":[[-3.18493,53.2516],[-3.18515,53.25167]]}},{"type":"Feature","id":93076,"properties":{"rag":"x","type":"OHL 230V 50 OAL","v":230},"geometry":{"type":"LineString","coordinates":[[-3.18414,53.24979],[-3.18412,53.2495],[-3.18376,53.24954]]}},{"type":"Feature","id":109744,"properties":{"rag":"a","type":"OHL 230V 50 OAL","v":230},"geometry":{"type":"LineString","coordinates":[[-3.17715,53.2446],[-3.17726,53.24503],[-3.17753,53.24549],[-3.17706,53.24561]]}},{"type":"Feature","id":109746,"properties":{"rag":"a","type":"OHL 230V 50 OAL","v":230},"geometry":{"type":"LineString","coordinates":[[-3.17878,53.24685],[-3.17923,53.24691],[-3.17976,53.24726],[-3.18022,53.24754],[-3.18083,53.24742]]}},{"type":"Feature","id":109750,"properties":{"rag":"a","type":"OHL 230V 50 OAL","v":230},"geometry":{"type":"LineString","coordinates":[[-3.17923,53.24691],[-3.17872,53.2466]]}},{"type":"Feature","id":109755,"properties":{"rag":"a","type":"OHL 230V 50 OAL","v":230},"geometry":{"type":"LineString","coordinates":[[-3.17753,53.24549],[-3.17786,53.24585],[-3.17829,53.24625],[-3.1787,53.24659]]}},{"type":"Feature","id":167634,"properties":{"rag":"g","type":"OHL 230V 95 ABC","v":230},"geometry":{"type":"LineString","coordinates":[[-3.16488,53.24164],[-3.16451,53.24143]]}}]}