{"type":"FeatureCollection","features":[{"type":"Feature","id":17512,"properties":{"rag":"r","type":"OHL 230V 50 OAL","v":230},"geometry":{"type":"LineString","coordinates":[[-3.46139,52.9928],[-3.46153,52.99287],[-3.46226,52.99297],[-3.46312,52.9931],[-3.46358,52.9933],[-3.46398,52.99346],[-3.4645,52.99367]]}},{"type":"Feature","id":17515,"properties":{"rag":"r","type":"OHL 230V 50 OAL","v":230},"geometry":{"type":"LineString","coordinates":[[-3.464,52.99064],[-3.46464,52.99049]]}},{"type":"Feature","id":24217,"properties":{"rag":"r","type":"OHL 230V 0.05 OAL","v":230},"geometry":{"type":"LineString","coordinates":[[-3.45415,52.99107],[-3.45412,52.99163],[-3.4535,52.99188]]}},{"type":"Feature","id":24221,"properties":{"rag":"r","type":"OHL 230V 0.05 OAL","v":230},"geometry":{"type":"LineString","coordinates":[[-3.46047,52.99767],[-3.46067,52.99732],[-3.46086,52.99697],[-3.46036,52.99686]]}},{"type":"Feature","id":24227,"properties":{"rag":"r","type":"OHL 230V 0.05 OAL","v":230},"geometry":{"type":"LineString","coordinates":[[-3.46046,52.99769],[-3.46027,52.998],[-3.46008,52.9983],[-3.46048,52.99842],[-3.46098,52.99856],[-3.46132,52.99874]]}},{"type":"Feature","id":24229,"properties":{"rag":"r","type":"OHL 230V 0.05 OAL","v":230},"geometry":{"type":"LineString","coordinates":[[-3.44977,52.98953],[-3.45005,52.98941],[-3.45045,52.98922]]}},{"type":"Feature","id":24628,"properties":{"rag":"r","type":"OHL 230V 0.05 OAL","v":230},"geometry":{"type":"LineString","coordinates":[[-3.45535,53.00057],[-3.45505,53.00099],[-3.45482,53.00134]]}},{"type":"Feature","id":39435,"properties":{"rag":"a","type":"UNKNOWN_LV_OHLine_M","v":230},"geometry":{"type":"LineString","coordinates":[[-3.46548,52.99],[-3.46569,52.98971],[-3.4663,52.98978]]}},{"type":"Feature","id":39436,"properties":{"rag":"a","type":"UNKNOWN_LV_OHLine_M","v":230},"geometry":{"type":"LineString","coordinates":[[-3.46564,52.99049],[-3.46572,52.99062],[-3.46605,52.99081],[-3.46684,52.99092]]}},{"type":"Feature","id":39439,"properties":{"rag":"a","type":"UNKNOWN_LV_OHLine_M","v":230},"geometry":{"type":"LineString","coordinates":[[-3.46547,52.99001],[-3.46523,52.99035],[-3.46465,52.99049]]}},{"type":"Feature","id":39441,"properties":{"rag":"a","type":"UNKNOWN_LV_OHLine_M","v":230},"geometry":{"type":"LineString","coordinates":[[-3.46523,52.99035],[-3.46572,52.99062]]}},{"type":"Feature","id":41213,"properties":{"rag":"r","type":"UNKNOWN_LV_OHLine_M","v":230},"geometry":{"type":"LineString","coordinates":[[-3.45535,53.00055],[-3.45517,53.00027],[-3.45496,52.99991]]}},{"type":"Feature","id":41227,"properties":{"rag":"r","type":"UNKNOWN_LV_OHLine_M","v":230},"geometry":{"type":"LineString","coordinates":[[-3.46358,52.99087],[-3.46308,52.99118],[-3.46328,52.99142]]}},{"type":"Feature","id":41228,"properties":{"rag":"r","type":"UNKNOWN_LV_OHLine_M","v":230},"geometry":{"type":"LineString","coordinates":[[-3.464,52.99064],[-3.46361,52.99085]]}},{"type":"Feature","id":41875,"properties":{"rag":"r","type":"UNKNOWN_LV_OHLine_M","v":230},"geometry":{"type":"LineString","coordinates":[[-3.47153,53.00003],[-3.4717,53.00011]]}},{"type":"Feature","id":47412,"properties":{"rag":"r","type":"Cable 230V 95 AL","v":230},"geometry":{"type":"LineString","coordinates":[[-3.46828,52.98915],[-3.46827,52.98914],[-3.4682,52.989],[-3.46796,52.98855],[-3.46794,52.98852],[-3.46792,52.98851],[-3.4679,52.9885],[-3.46788,52.9885],[-3.46788,52.9885]]}},{"type":"Feature","id":82401,"properties":{"rag":"r","type":"OHL 230V 0.025 OCU","v":230},"geometry":{"type":"LineString","coordinates":[[-3.46642,52.99776],[-3.4659,52.99807],[-3.4663,52.9984]]}},{"type":"Feature","id":108886,"properties":{"rag":"a","type":"OHL 230V 50 OAL","v":230},"geometry":{"type":"LineString","coordinates":[[-3.46465,52.99049],[-3.46466,52.99059]]}},{"type":"Feature","id":168001,"properties":{"rag":"g","type":"UNKNOWN_LV_OHLine_M","v":230},"geometry":{"type":"LineString","coordinates":[[-3.46282,52.98875],[-3.46327,52.98872],[-3.46372,52.9886]]}},{"type":"Feature","id":168002,"properties":{"rag":"g","type":"UNKNOWN_LV_OHLine_M","v":230},"geometry":{"type":"LineString","coordinates":[[-3.46946,52.99225],[-3.46915,52.99222]]}},{"type":"Feature","id":168003,"properties":{"rag":"g","type":"UNKNOWN_LV_OHLine_M","v":230},"geometry":{"type":"LineString","coordinates":[[-3.46319,52.98704],[-3.46378,52.98754],[-3.46425,52.98796],[-3.46487,52.98783],[-3.46572,52.98795],[-3.46558,52.98835]]}},{"type":"Feature","id":168004,"properties":{"rag":"g","type":"UNKNOWN_LV_OHLine_M","v":230},"geometry":{"type":"LineString","coordinates":[[-3.46375,52.9886],[-3.46378,52.98856]]}},{"type":"Feature","id":207297,"properties":{"rag":"g","type":"OHL 230V 35 ABC","v":230},"geometry":{"type":"LineString","coordinates":[[-3.46558,52.98835],[-3.46515,52.98849]]}}]}