{"type":"FeatureCollection","features":[{"type":"Feature","id":21671,"properties":{"rag":"r","type":"OHL 230V 50 OAL","v":230},"geometry":{"type":"LineString","coordinates":[[-3.58181,53.24504],[-3.5814,53.2453],[-3.58093,53.24561],[-3.58067,53.24595],[-3.58049,53.24635],[-3.58033,53.24677],[-3.58014,53.24725],[-3.57959,53.24738]]}},{"type":"Feature","id":21676,"properties":{"rag":"r","type":"OHL 230V 50 OAL","v":230},"geometry":{"type":"LineString","coordinates":[[-3.58366,53.25052],[-3.58384,53.25012],[-3.58407,53.24958],[-3.58467,53.24947],[-3.5853,53.24931]]}},{"type":"Feature","id":21678,"properties":{"rag":"r","type":"OHL 230V 50 OAL","v":230},"geometry":{"type":"LineString","coordinates":[[-3.59971,53.24317],[-3.59927,53.24278]]}},{"type":"Feature","id":21690,"properties":{"rag":"r","type":"OHL 230V 50 OAL","v":230},"geometry":{"type":"LineString","coordinates":[[-3.59213,53.24469],[-3.59204,53.24501]]}},{"type":"Feature","id":21712,"properties":{"rag":"r","type":"OHL 230V 50 OAL","v":230},"geometry":{"type":"LineString","coordinates":[[-3.60058,53.24396],[-3.60081,53.24416]]}},{"type":"Feature","id":23074,"properties":{"rag":"r","type":"OHL 230V 50 OAL","v":230},"geometry":{"type":"LineString","coordinates":[[-3.59848,53.25121],[-3.59771,53.25124]]}},{"type":"Feature","id":23093,"properties":{"rag":"r","type":"OHL 230V 50 OAL","v":230},"geometry":{"type":"LineString","coordinates":[[-3.5952,53.25134],[-3.59535,53.25134]]}},{"type":"Feature","id":26641,"properties":{"rag":"r","type":"OHL 230V 0.05 OAL","v":230},"geometry":{"type":"LineString","coordinates":[[-3.59845,53.24281],[-3.5979,53.24283]]}},{"type":"Feature","id":26644,"properties":{"rag":"r","type":"OHL 230V 0.05 OAL","v":230},"geometry":{"type":"LineString","coordinates":[[-3.59971,53.24317],[-3.60007,53.24352],[-3.60022,53.24365]]}},{"type":"Feature","id":27461,"properties":{"rag":"r","type":"OHL 230V 0.05 OAL","v":230},"geometry":{"type":"LineString","coordinates":[[-3.59535,53.25134],[-3.59615,53.25131],[-3.59629,53.25132],[-3.59695,53.25129],[-3.59771,53.25124]]}},{"type":"Feature","id":27467,"properties":{"rag":"r","type":"OHL 230V 0.05 OAL","v":230},"geometry":{"type":"LineString","coordinates":[[-3.59848,53.25121],[-3.5989,53.2511],[-3.59943,53.25095]]}},{"type":"Feature","id":45116,"properties":{"rag":"r","type":"UNKNOWN_LV_OHLine_M","v":230},"geometry":{"type":"LineString","coordinates":[[-3.5979,53.24283],[-3.59769,53.24324]]}},{"type":"Feature","id":45124,"properties":{"rag":"r","type":"UNKNOWN_LV_OHLine_M","v":230},"geometry":{"type":"LineString","coordinates":[[-3.59213,53.24469],[-3.59219,53.24455]]}},{"type":"Feature","id":45126,"properties":{"rag":"r","type":"UNKNOWN_LV_OHLine_M","v":230},"geometry":{"type":"LineString","coordinates":[[-3.58426,53.24411],[-3.58368,53.24432]]}},{"type":"Feature","id":45129,"properties":{"rag":"r","type":"UNKNOWN_LV_OHLine_M","v":230},"geometry":{"type":"LineString","coordinates":[[-3.58429,53.24409],[-3.58457,53.24402]]}},{"type":"Feature","id":46409,"properties":{"rag":"r","type":"UNKNOWN_LV_OHLine_M","v":230},"geometry":{"type":"LineString","coordinates":[[-3.59535,53.25134],[-3.59551,53.25137]]}},{"type":"Feature","id":55021,"properties":{"rag":"r","type":"Cable 230V 95 AL","v":230},"geometry":{"type":"LineString","coordinates":[[-3.59845,53.24281],[-3.59858,53.24278],[-3.59877,53.24273],[-3.59877,53.24273],[-3.59877,53.24273],[-3.59891,53.24269],[-3.59891,53.24269],[-3.59891,53.24269],[-3.59891,53.24269],[-3.59891,53.24269],[-3.59891,53.24269],[-3.59891,53.24269],[-3.59891,53.24269],[-3.59891,53.24269],[-3.59892,53.24269],[-3.59892,53.24269],[-3.59892,53.24269],[-3.59892,53.24269],[-3.59892,53.24269],[-3.59892,53.24269],[-3.59892,53.24269],[-3.59892,53.24269],[-3.59892,53.24269],[-3.59908,53.24273],[-3.59913,53.24274],[-3.59926,53.24277]]}},{"type":"Feature","id":82231,"properties":{"rag":"r","type":"OHL 230V 32 OAL","v":230},"geometry":{"type":"LineString","coordinates":[[-3.60022,53.24365],[-3.60058,53.24396]]}},{"type":"Feature","id":94646,"properties":{"rag":"r","type":"Cable 230V 25 AL ACT","v":230},"geometry":{"type":"LineString","coordinates":[[-3.59551,53.25137],[-3.59546,53.25144]]}}]}