{"type":"FeatureCollection","features":[{"type":"Feature","id":17879,"properties":{"rag":"r","type":"OHL 230V 50 OAL","v":230},"geometry":{"type":"LineString","coordinates":[[-2.9432,52.99968],[-2.94311,53.00015]]}},{"type":"Feature","id":24359,"properties":{"rag":"r","type":"OHL 230V 0.05 OAL","v":230},"geometry":{"type":"LineString","coordinates":[[-2.9432,52.99968],[-2.9432,52.99968],[-2.94327,52.9993],[-2.94331,52.99893],[-2.94389,52.99874]]}},{"type":"Feature","id":42282,"properties":{"rag":"r","type":"UNKNOWN_LV_OHLine_M","v":230},"geometry":{"type":"LineString","coordinates":[[-2.94311,53.00017],[-2.94301,53.00072]]}},{"type":"Feature","id":114740,"properties":{"rag":"g","type":"OHL 230V 50 OAL","v":230},"geometry":{"type":"LineString","coordinates":[[-2.94052,52.99861],[-2.94041,52.9987],[-2.94017,52.99891],[-2.9399,52.99916]]}},{"type":"Feature","id":168074,"properties":{"rag":"g","type":"UNKNOWN_LV_OHLine_M","v":230},"geometry":{"type":"LineString","coordinates":[[-2.92724,52.99056],[-2.92697,52.99083]]}}]}