{"type":"FeatureCollection","features":[{"type":"Feature","id":19191,"properties":{"rag":"r","type":"OHL 230V 50 OAL","v":230},"geometry":{"type":"LineString","coordinates":[[-2.6995,53.07967],[-2.6992,53.07976],[-2.69902,53.08011],[-2.69903,53.08054],[-2.69902,53.08101],[-2.69907,53.08142]]}},{"type":"Feature","id":19194,"properties":{"rag":"r","type":"OHL 230V 50 OAL","v":230},"geometry":{"type":"LineString","coordinates":[[-2.69903,53.08054],[-2.69877,53.08056]]}},{"type":"Feature","id":19195,"properties":{"rag":"r","type":"OHL 230V 50 OAL","v":230},"geometry":{"type":"LineString","coordinates":[[-2.69985,53.07537],[-2.69966,53.07538],[-2.70031,53.07568]]}},{"type":"Feature","id":19196,"properties":{"rag":"r","type":"OHL 230V 50 OAL","v":230},"geometry":{"type":"LineString","coordinates":[[-2.69845,53.07516],[-2.69906,53.07527],[-2.69966,53.07538]]}},{"type":"Feature","id":19197,"properties":{"rag":"r","type":"OHL 230V 50 OAL","v":230},"geometry":{"type":"LineString","coordinates":[[-2.69902,53.08011],[-2.69845,53.08014],[-2.69774,53.08019],[-2.69736,53.08022]]}},{"type":"Feature","id":84255,"properties":{"rag":"r","type":"Cable 230V 185 AL WAVE","v":230},"geometry":{"type":"LineString","coordinates":[[-2.69877,53.08056],[-2.69797,53.08067],[-2.69796,53.08067],[-2.69796,53.08067],[-2.69796,53.08068],[-2.69795,53.08069]]}},{"type":"Feature","id":115022,"properties":{"rag":"g","type":"OHL 230V 50 OAL","v":230},"geometry":{"type":"LineString","coordinates":[[-2.68455,53.07919],[-2.68381,53.07943]]}}]}