{"type":"FeatureCollection","features":[{"type":"Feature","id":40179,"properties":{"rag":"a","type":"UNKNOWN_LV_OHLine_M","v":230},"geometry":{"type":"LineString","coordinates":[[-3.24054,53.1733],[-3.24042,53.17275],[-3.23981,53.17241]]}},{"type":"Feature","id":52818,"properties":{"rag":"r","type":"Cable 230V 95 AL","v":230},"geometry":{"type":"LineString","coordinates":[[-3.23378,53.17087],[-3.23378,53.17087],[-3.23378,53.17087],[-3.23364,53.17079],[-3.23356,53.17076],[-3.23347,53.17074]]}},{"type":"Feature","id":109556,"properties":{"rag":"a","type":"OHL 230V 50 OAL","v":230},"geometry":{"type":"LineString","coordinates":[[-3.23858,53.17485],[-3.23943,53.17465],[-3.23984,53.17418],[-3.24011,53.17387],[-3.24054,53.1733],[-3.24,53.17346],[-3.23931,53.17322],[-3.23846,53.17317],[-3.23745,53.17311]]}}]}