{"type":"FeatureCollection","features":[{"type":"Feature","id":6937,"properties":{"rag":"g","type":"Cable 230V 95 AL","v":230},"geometry":{"type":"LineString","coordinates":[[-3.42146,53.27129],[-3.42134,53.27119],[-3.42133,53.27119],[-3.42133,53.27118],[-3.42133,53.27118],[-3.42133,53.27118],[-3.42145,53.271],[-3.42145,53.27099]]}},{"type":"Feature","id":22822,"properties":{"rag":"r","type":"OHL 230V 50 OAL","v":230},"geometry":{"type":"LineString","coordinates":[[-3.42575,53.26673],[-3.42543,53.26638]]}},{"type":"Feature","id":22837,"properties":{"rag":"r","type":"OHL 230V 50 OAL","v":230},"geometry":{"type":"LineString","coordinates":[[-3.40998,53.26975],[-3.41019,53.2702]]}},{"type":"Feature","id":22842,"properties":{"rag":"r","type":"OHL 230V 50 OAL","v":230},"geometry":{"type":"LineString","coordinates":[[-3.40983,53.26939],[-3.40949,53.26902]]}},{"type":"Feature","id":27334,"properties":{"rag":"r","type":"OHL 230V 0.05 OAL","v":230},"geometry":{"type":"LineString","coordinates":[[-3.41169,53.26449],[-3.41181,53.26462],[-3.412,53.26483],[-3.41234,53.26522]]}},{"type":"Feature","id":46135,"properties":{"rag":"r","type":"UNKNOWN_LV_OHLine_M","v":230},"geometry":{"type":"LineString","coordinates":[[-3.42539,53.26632],[-3.42543,53.26638],[-3.42586,53.26627],[-3.42635,53.26616],[-3.4268,53.26641],[-3.42742,53.26625]]}},{"type":"Feature","id":46140,"properties":{"rag":"r","type":"UNKNOWN_LV_OHLine_M","v":230},"geometry":{"type":"LineString","coordinates":[[-3.41887,53.27036],[-3.41864,53.27003]]}},{"type":"Feature","id":46144,"properties":{"rag":"r","type":"UNKNOWN_LV_OHLine_M","v":230},"geometry":{"type":"LineString","coordinates":[[-3.42597,53.26699],[-3.42575,53.26673]]}},{"type":"Feature","id":46147,"properties":{"rag":"r","type":"UNKNOWN_LV_OHLine_M","v":230},"geometry":{"type":"LineString","coordinates":[[-3.4268,53.26641],[-3.42697,53.26652]]}},{"type":"Feature","id":46148,"properties":{"rag":"r","type":"UNKNOWN_LV_OHLine_M","v":230},"geometry":{"type":"LineString","coordinates":[[-3.41269,53.26529],[-3.41234,53.26522],[-3.41269,53.26561],[-3.41294,53.26586]]}},{"type":"Feature","id":58858,"properties":{"rag":"r","type":"Cable 230V 95 AL","v":230},"geometry":{"type":"LineString","coordinates":[[-3.42886,53.26732],[-3.42873,53.26728],[-3.42756,53.26706],[-3.42738,53.26703],[-3.42702,53.267],[-3.42679,53.26695],[-3.42678,53.26695],[-3.42661,53.26688],[-3.42657,53.26679],[-3.42662,53.26678],[-3.42672,53.26676],[-3.42671,53.26669],[-3.42666,53.26653],[-3.42658,53.26646],[-3.42653,53.26639],[-3.42635,53.26616]]}},{"type":"Feature","id":58912,"properties":{"rag":"r","type":"Cable 230V 95 AL","v":230},"geometry":{"type":"LineString","coordinates":[[-3.40985,53.2694],[-3.40987,53.2694],[-3.40989,53.2694],[-3.4099,53.26942],[-3.40991,53.26945],[-3.40993,53.26963],[-3.40994,53.26966],[-3.40998,53.26975]]}},{"type":"Feature","id":94587,"properties":{"rag":"r","type":"Cable 230V 25 AL ACT","v":230},"geometry":{"type":"LineString","coordinates":[[-3.42433,53.27414],[-3.42489,53.2738]]}},{"type":"Feature","id":95810,"properties":{"rag":"g","type":"OHL 230V 0.05 OAL","v":230},"geometry":{"type":"LineString","coordinates":[[-3.4288,53.27218],[-3.42829,53.2723],[-3.42771,53.27237],[-3.42706,53.27255],[-3.42647,53.27276],[-3.4258,53.27283],[-3.42513,53.27291]]}},{"type":"Feature","id":95812,"properties":{"rag":"g","type":"OHL 230V 0.05 OAL","v":230},"geometry":{"type":"LineString","coordinates":[[-3.41668,53.27041],[-3.41666,53.27051],[-3.41685,53.2709]]}},{"type":"Feature","id":95819,"properties":{"rag":"g","type":"OHL 230V 0.05 OAL","v":230},"geometry":{"type":"LineString","coordinates":[[-3.42018,53.26832],[-3.41976,53.2681],[-3.41931,53.26788]]}},{"type":"Feature","id":101169,"properties":{"rag":"a","type":"Cable 230V 95 AL","v":230},"geometry":{"type":"LineString","coordinates":[[-3.40676,53.2704],[-3.40666,53.2703],[-3.40652,53.27016],[-3.4065,53.27014],[-3.40644,53.27007],[-3.40642,53.27005],[-3.40642,53.27005],[-3.40642,53.27004],[-3.40642,53.27003],[-3.40642,53.27003],[-3.40644,53.26997]]}},{"type":"Feature","id":110813,"properties":{"rag":"a","type":"OHL 230V 0.05 OAL","v":230},"geometry":{"type":"LineString","coordinates":[[-3.40766,53.27046],[-3.40739,53.27018],[-3.40701,53.26979],[-3.40644,53.26997]]}},{"type":"Feature","id":116040,"properties":{"rag":"g","type":"OHL 230V 50 OAL","v":230},"geometry":{"type":"LineString","coordinates":[[-3.42146,53.27129],[-3.42082,53.27129]]}},{"type":"Feature","id":116041,"properties":{"rag":"g","type":"OHL 230V 50 OAL","v":230},"geometry":{"type":"LineString","coordinates":[[-3.41931,53.26788],[-3.41863,53.26782],[-3.41805,53.26776],[-3.41741,53.2677],[-3.41685,53.26765],[-3.41634,53.26761],[-3.41572,53.2676],[-3.41507,53.26774]]}},{"type":"Feature","id":167785,"properties":{"rag":"g","type":"OHL 230V 95 ABC","v":230},"geometry":{"type":"LineString","coordinates":[[-3.41741,53.26757],[-3.41741,53.2677]]}},{"type":"Feature","id":169611,"properties":{"rag":"g","type":"UNKNOWN_LV_OHLine_M","v":230},"geometry":{"type":"LineString","coordinates":[[-3.41685,53.2709],[-3.41688,53.27106]]}},{"type":"Feature","id":169612,"properties":{"rag":"g","type":"UNKNOWN_LV_OHLine_M","v":230},"geometry":{"type":"LineString","coordinates":[[-3.42199,53.27132],[-3.42146,53.27129]]}},{"type":"Feature","id":169624,"properties":{"rag":"g","type":"UNKNOWN_LV_OHLine_M","v":230},"geometry":{"type":"LineString","coordinates":[[-3.42647,53.27276],[-3.42636,53.27283]]}}]}